ndu_gate_camera/__init__.py
ndu_gate_camera/ndu_camera.py
ndu_gate_camera/updater.py
ndu_gate_camera/api/__init__.py
ndu_gate_camera/api/ndu_camera_runner.py
ndu_gate_camera/api/result_handler.py
ndu_gate_camera/api/runner_settings.py
ndu_gate_camera/api/video_source.py
ndu_gate_camera/camera/__init__.py
ndu_gate_camera/camera/frame_pre_processors.py
ndu_gate_camera/camera/ndu_camera_service.py
ndu_gate_camera/camera/ndu_logger.py
ndu_gate_camera/camera/roi_manager.py
ndu_gate_camera/camera/result_handlers/__init__.py
ndu_gate_camera/camera/result_handlers/platform_handler.py
ndu_gate_camera/camera/result_handlers/result_handler_file.py
ndu_gate_camera/camera/result_handlers/result_handler_mqtt.py
ndu_gate_camera/camera/result_handlers/result_handler_socket.py
ndu_gate_camera/camera/video_sources/__init__.py
ndu_gate_camera/camera/video_sources/camera_video_source.py
ndu_gate_camera/camera/video_sources/file_video_source.py
ndu_gate_camera/camera/video_sources/image_video_source.py
ndu_gate_camera/camera/video_sources/ip_camera_video_source.py
ndu_gate_camera/camera/video_sources/pi_camera_video_source.py
ndu_gate_camera/camera/video_sources/youtube_video_source.py
ndu_gate_camera/runners/__init__.py
ndu_gate_camera/utility/__init__.py
ndu_gate_camera/utility/constants.py
ndu_gate_camera/utility/download_zipped_helper.py
ndu_gate_camera/utility/file_helper.py
ndu_gate_camera/utility/geometry_helper.py
ndu_gate_camera/utility/image_helper.py
ndu_gate_camera/utility/ndu_utility.py
ndu_gate_camera/utility/onnx_helper.py
ndu_gate_camera/utility/string_helper.py
ndu_gate_camera/utility/thread_helper.py
ndu_gate_camera/utility/yolo_helper.py
ndu_gate_camera-0.1.9.18.dist-info/LICENSE
ndu_gate_camera-0.1.9.18.dist-info/METADATA
ndu_gate_camera-0.1.9.18.dist-info/WHEEL
ndu_gate_camera-0.1.9.18.dist-info/entry_points.txt
ndu_gate_camera-0.1.9.18.dist-info/top_level.txt
ndu_gate_camera-0.1.9.18.dist-info/RECORD
