Metadata-Version: 2.1
Name: ndu-gate-camera
Version: 0.1.9.18
Summary: NDU Gate Camera Service
Home-page: https://github.com/netcadlabs/ndu-gate
Author: Netcad Innovation Labs @NETCAD
Author-email: netcadinnovationlabs@gmail.com
License: Apache Software License (Apache Software License 2.0)
Download-URL: https://github.com/netcadlabs/ndu-gate/archive/0.1.9.18.tar.gz
Platform: UNKNOWN
Requires-Python: >=3.5
License-File: LICENSE
Requires-Dist: opencv-python
Requires-Dist: opencv-contrib-python
Requires-Dist: onnx
Requires-Dist: onnxruntime
Requires-Dist: pip
Requires-Dist: gdown
Requires-Dist: PyYAML
Requires-Dist: simplejson
Requires-Dist: vidgear (==0.1.9)
Requires-Dist: pyzmq
Requires-Dist: filterpy (==1.4.5)
Requires-Dist: paho-mqtt
Requires-Dist: requests
Requires-Dist: mmh3
